LICENSE
MANIFEST.in
README.md
setup.py
amautta_project/__init__.py
amautta_project/cli.py
amautta_project/docker_modified.py
amautta_project/entity_generator.py
amautta_project/envdocker.py
amautta_project/git_generator.py
amautta_project/main_modified.py
amautta_project/microservice_generator.py
amautta_project/migration_generator.py
amautta_project/project_generator.py
amautta_project/readme_modified.py
amautta_project/site_generator.py
amautta_project/templates/dockerfile.txt
amautta_project/templates/env.txt
amautta_project/templates/requirements.txt
amautta_project/templates/entity/entity.txt
amautta_project/templates/entity/input_dto.txt
amautta_project/templates/entity/insert_validation.txt
amautta_project/templates/entity/model.txt
amautta_project/templates/entity/output_dto.txt
amautta_project/templates/entity/repository.txt
amautta_project/templates/entity/repository_impl.txt
amautta_project/templates/entity/router.txt
amautta_project/templates/entity/service.txt
amautta_project/templates/entity/update_validation.txt
amautta_project/templates/entity/use_case_create.txt
amautta_project/templates/entity/use_case_delete.txt
amautta_project/templates/entity/use_case_get_all.txt
amautta_project/templates/entity/use_case_get_by_id.txt
amautta_project/templates/entity/use_case_update.txt
amautta_project/templates/entity/value_object_datetime.txt
amautta_project/templates/microservice/alembic.ini.txt
amautta_project/templates/microservice/alembic_env.txt
amautta_project/templates/microservice/alembic_script.txt
amautta_project/templates/microservice/command.txt
amautta_project/templates/microservice/command_seeder.txt
amautta_project/templates/microservice/connections.txt
amautta_project/templates/microservice/database_settings.txt
amautta_project/templates/microservice/domain_filter.txt
amautta_project/templates/microservice/handler.txt
amautta_project/templates/microservice/input_filter.txt
amautta_project/templates/microservice/main.txt
quipus_generate.egg-info/PKG-INFO
quipus_generate.egg-info/SOURCES.txt
quipus_generate.egg-info/dependency_links.txt
quipus_generate.egg-info/entry_points.txt
quipus_generate.egg-info/requires.txt
quipus_generate.egg-info/top_level.txt