Metadata-Version: 2.1
Name: quipus-generate
Version: 1.1.3
Summary: Generador de proyectos FastAPI con arquitectura Hexagonal.
Author: Juan David Corrales Saldarriaga
Author-email: sistemas@amauttasistems.com
License: Proprietary
Classifier: Programming Language :: Python :: 3
Classifier: License :: Other/Proprietary License
Classifier: Operating System :: OS Independent
Requires-Python: >=3.8
License-File: LICENSE
Requires-Dist: inflection
Requires-Dist: ruamel.yaml
Requires-Dist: Jinja2
